azureml/__init__.py
azureml/automl/__init__.py
azureml/automl/runtime/LICENSE_limit_function_call
azureml/automl/runtime/__init__.py
azureml/automl/runtime/_aml_forecasting_horizon_metrics.py
azureml/automl/runtime/_automl_forecast_freq.py
azureml/automl/runtime/_common_training_utilities.py
azureml/automl/runtime/_data_splitting_utilities.py
azureml/automl/runtime/_data_transformation_utilities.py
azureml/automl/runtime/_engineered_feature_names.py
azureml/automl/runtime/_feature_sweeped_state_container.py
azureml/automl/runtime/_featurization_execution.py
azureml/automl/runtime/_featurization_execution_timeseries.py
azureml/automl/runtime/_featurization_orchestration.py
azureml/automl/runtime/_forecasting_log_transform_utilities.py
azureml/automl/runtime/_forecasting_logging_utilities.py
azureml/automl/runtime/_freq_aggregator.py
azureml/automl/runtime/_grain_preparer.py
azureml/automl/runtime/_grain_stat_generator.py
azureml/automl/runtime/_metrics_logging.py
azureml/automl/runtime/_runtime_params.py
azureml/automl/runtime/_shared_package_legacy_import.py
azureml/automl/runtime/_time_series_data_config.py
azureml/automl/runtime/_time_series_data_set.py
azureml/automl/runtime/_time_series_training_utilities.py
azureml/automl/runtime/_timeseries_id_detection_utilities.py
azureml/automl/runtime/_validation_strategy_selector.py
azureml/automl/runtime/_version.py
azureml/automl/runtime/automl_pipeline.py
azureml/automl/runtime/automl_run_context.py
azureml/automl/runtime/cpu_utilities.py
azureml/automl/runtime/data_cleaning.py
azureml/automl/runtime/data_context.py
azureml/automl/runtime/data_transformation.py
azureml/automl/runtime/dataprep_utilities.py
azureml/automl/runtime/ensemble_base.py
azureml/automl/runtime/experiment_store.py
azureml/automl/runtime/faults_verifier.py
azureml/automl/runtime/faults_verifier_message.json
azureml/automl/runtime/feature_skus_utilities.py
azureml/automl/runtime/featurization_info_provider.py
azureml/automl/runtime/fit_output.py
azureml_automl_runtime-1.60.0.dist-info/licenses/LICENSE.txt
azureml_automl_runtime-1.60.0.dist-info/METADATA
azureml_automl_runtime-1.60.0.dist-info/WHEEL
azureml_automl_runtime-1.60.0.dist-info/top_level.txt
azureml_automl_runtime-1.60.0.dist-info/RECORD
